regex4numbers/README.MD
regex4numbers/__init__.py
regex4numbers/requirements.txt
regex4numbers/thirdparty.json
regex4numbers-0.10.dist-info/LICENSE.rst
regex4numbers-0.10.dist-info/METADATA
regex4numbers-0.10.dist-info/WHEEL
regex4numbers-0.10.dist-info/top_level.txt
regex4numbers-0.10.dist-info/RECORD
