Metadata-Version: 2.1
Name: regex4numbers
Version: 0.10
Summary: generates regex for numbers (ge / le / in range)
Home-page: https://github.com/hansalemaos/regex4numbers
Author: Johannes Fischer
Author-email: aulasparticularesdealemaosp@gmail.com
License: MIT
Keywords: regex,numbers
Classifier: Development Status :: 4 - Beta
Classifier: Programming Language :: Python :: 3 :: Only
Classifier: Programming Language :: Python :: 3.10
Classifier: Topic :: Software Development :: Libraries :: Python Modules
Classifier: Topic :: Utilities
License-File: LICENSE.rst
